plonetheme.spot-1.1-py2.7-nspkg.pth
plonetheme/spot/__init__.py
plonetheme/spot/configure.zcml
plonetheme/spot/interfaces.py
plonetheme/spot/setuphandlers.py
plonetheme/spot/testing.py
plonetheme/spot/browser/__init__.py
plonetheme/spot/browser/configure.zcml
plonetheme/spot/browser/overrides/.gitkeep
plonetheme/spot/browser/static/.gitkeep
plonetheme/spot/locales/plonetheme.spot.pot
plonetheme/spot/locales/update.sh
plonetheme/spot/profiles/default/browserlayer.xml
plonetheme/spot/profiles/default/metadata.xml
plonetheme/spot/profiles/default/theme.xml
plonetheme/spot/profiles/uninstall/browserlayer.xml
plonetheme/spot/profiles/uninstall/theme.xml
plonetheme/spot/tests/__init__.py
plonetheme/spot/tests/test_robot.py
plonetheme/spot/tests/test_setup.py
plonetheme/spot/tests/robot/test_example.robot
plonetheme/spot/theme/index.html
plonetheme/spot/theme/manifest.cfg
plonetheme/spot/theme/preview.png
plonetheme/spot/theme/rules.xml
plonetheme/spot/theme/css/.DS_Store
plonetheme/spot/theme/css/bootstrap.min.css
plonetheme/spot/theme/css/font-awesome.min.css
plonetheme/spot/theme/css/main.css
plonetheme/spot/theme/fonts/.DS_Store
plonetheme/spot/theme/fonts/FontAwesome.otf
plonetheme/spot/theme/fonts/fontawesome-webfont.eot
plonetheme/spot/theme/fonts/fontawesome-webfont.svg
plonetheme/spot/theme/fonts/fontawesome-webfont.ttf
plonetheme/spot/theme/fonts/fontawesome-webfont.woff
plonetheme/spot/theme/fonts/glyphicons-halflings-regular.eot
plonetheme/spot/theme/fonts/glyphicons-halflings-regular.svg
plonetheme/spot/theme/fonts/glyphicons-halflings-regular.ttf
plonetheme/spot/theme/fonts/glyphicons-halflings-regular.woff
plonetheme/spot/theme/img/.DS_Store
plonetheme/spot/theme/img/header-bg.jpg
plonetheme/spot/theme/js/.DS_Store
plonetheme/spot/theme/js/Chart.js
plonetheme/spot/theme/js/bootstrap.min.js
plonetheme/spot/theme/less/main.less
plonetheme/spot/theme/less/spot-compiled.css.map
plonetheme/spot/theme/less/spot.css
plonetheme.spot-1.1.dist-info/DESCRIPTION.rst
plonetheme.spot-1.1.dist-info/METADATA
plonetheme.spot-1.1.dist-info/RECORD
plonetheme.spot-1.1.dist-info/WHEEL
plonetheme.spot-1.1.dist-info/entry_points.txt
plonetheme.spot-1.1.dist-info/metadata.json
plonetheme.spot-1.1.dist-info/namespace_packages.txt
plonetheme.spot-1.1.dist-info/top_level.txt
